{
  "method": "ewc",
  "acc_matrix": [
    [
      0.764,
      0.0,
      0.0,
      0.0,
      0.0
    ],
    [
      0.0335,
      0.759,
      0.0,
      0.0,
      0.0
    ],
    [
      0.0,
      0.075,
      0.7365,
      0.0,
      0.0
    ],
    [
      0.0,
      0.0025,
      0.0535,
      0.708,
      0.0
    ],
    [
      0.0,
      0.0,
      0.0,
      0.015,
      0.782
    ]
  ],
  "aa": 15.94,
  "bwt": -73.81,
  "task_times": [
    51.13,
    56.05,
    60.54,
    65.65,
    69.66
  ]
}